pydash/__init__.py
pydash/arrays.py
pydash/collections.py
pydash/exceptions.py
pydash/functions.py
pydash/helpers.py
pydash/numerical.py
pydash/objects.py
pydash/predicates.py
pydash/py.typed
pydash/strings.py
pydash/types.py
pydash/utilities.py
pydash/chaining/__init__.py
pydash/chaining/all_funcs.py
pydash/chaining/all_funcs.pyi
pydash/chaining/chaining.py
pydash-8.0.3.dist-info/AUTHORS.rst
pydash-8.0.3.dist-info/LICENSE.rst
pydash-8.0.3.dist-info/METADATA
pydash-8.0.3.dist-info/WHEEL
pydash-8.0.3.dist-info/top_level.txt
pydash-8.0.3.dist-info/RECORD
