Metadata-Version: 2.1
Name: pydash
Version: 8.0.3
Summary: The kitchen sink of Python utility libraries for doing "stuff" in a functional way. Based on the Lo-Dash Javascript library.
Author-email: Derrick Gilland <dgilland@gmail.com>
License: MIT License
Project-URL: Homepage, https://github.com/dgilland/pydash
Project-URL: Documentation, https://pydash.readthedocs.org
Project-URL: Repository, https://github.com/dgilland/pydash
Project-URL: Issues, https://github.com/dgilland/pydash/issues
Project-URL: Changelog, https://github.com/dgilland/pydash/blob/develop/CHANGELOG.rst
Keywords: pydash,utility,functional,lodash,underscore
Classifier: Development Status :: 5 - Production/Stable
Classifier: License :: OSI Approved :: MIT License
Classifier: Intended Audience :: Developers
Classifier: Operating System :: OS Independent
Classifier: Programming Language :: Python
Classifier: Programming Language :: Python :: 3
Classifier: Programming Language :: Python :: 3.8
Classifier: Programming Language :: Python :: 3.9
Classifier: Programming Language :: Python :: 3.10
Classifier: Programming Language :: Python :: 3.11
Classifier: Programming Language :: Python :: 3.12
Classifier: Topic :: Software Development :: Libraries
Classifier: Topic :: Software Development :: Libraries :: Python Modules
Classifier: Topic :: Utilities
Requires-Python: >=3.8
License-File: LICENSE.rst
License-File: AUTHORS.rst
Requires-Dist: typing-extensions!=4.6.0,>3.10
Provides-Extra: dev
Requires-Dist: build; extra == "dev"
Requires-Dist: coverage; extra == "dev"
Requires-Dist: ruff; extra == "dev"
Requires-Dist: furo; extra == "dev"
Requires-Dist: invoke; extra == "dev"
Requires-Dist: mypy; extra == "dev"
Requires-Dist: pytest; extra == "dev"
Requires-Dist: pytest-mypy-testing; extra == "dev"
Requires-Dist: pytest-cov; extra == "dev"
Requires-Dist: sphinx; extra == "dev"
Requires-Dist: tox; extra == "dev"
Requires-Dist: twine; extra == "dev"
Requires-Dist: wheel; extra == "dev"
Requires-Dist: sphinx-autodoc-typehints; extra == "dev"
